castenv/__init__.py
castenv/tests/__init__.py
castenv/tests/test_castenv.py
castenv-0.3.0.dist-info/METADATA
castenv-0.3.0.dist-info/WHEEL
castenv-0.3.0.dist-info/licenses/LICENSE
castenv-0.3.0.dist-info/RECORD
