Metadata-Version: 2.4
Name: castenv
Version: 0.3.0
Summary: Smart environment loader with robust casting/normalization. Layers: decouple → dotenv → os.environ.
License: MIT
License-File: LICENSE
Keywords: env,dotenv,decouple,config,settings,casting,normalization
Author: Ryan Julyan
Author-email: ryan@julyan.biz
Requires-Python: >=3.9,<4.0
Classifier: Intended Audience :: Developers
Classifier: License :: OSI Approved :: MIT License
Classifier: Programming Language :: Python :: 3
Classifier: Programming Language :: Python :: 3.9
Classifier: Programming Language :: Python :: 3.10
Classifier: Programming Language :: Python :: 3.11
Classifier: Programming Language :: Python :: 3.12
Classifier: Programming Language :: Python :: 3.13
Classifier: Programming Language :: Python :: 3.14
Classifier: Programming Language :: Python :: 3 :: Only
Classifier: Programming Language :: Python :: 3.8
Classifier: Topic :: Software Development :: Libraries :: Python Modules
Provides-Extra: decouple
Provides-Extra: dotenv
Requires-Dist: python-decouple (>=3.8) ; extra == "decouple"
Requires-Dist: python-dotenv (>=1.1.1) ; extra == "dotenv"
Project-URL: Homepage, https://pypi.org/project/castenv/
Project-URL: Repository, https://github.com/systemizing-solutions/castenv
